whisper_ai_zxs/__init__.py
whisper_ai_zxs/address_parser.py
whisper_ai_zxs/agent_servicer.py
whisper_ai_zxs/agent_servicer_SZ.py
whisper_ai_zxs/agent_servicer_TestStub.py
whisper_ai_zxs/agent_servicer_YD.py
whisper_ai_zxs/agent_test.py
whisper_ai_zxs/agent_trainer.py
whisper_ai_zxs/api_wangdiantong.py
whisper_ai_zxs/logging_config.py
whisper_ai_zxs/register_function.py
whisper_ai_zxs/register_function_chinese.py
whisper_ai_zxs/whisper_ai.py
whisper_ai_zxs/whisper_azure.py
whisper_ai_zxs/whisper_db.py
whisper_ai_zxs/whisper_db_pool.py
whisper_ai_zxs/whisper_function.py
whisper_ai_zxs/whisper_handler.py
whisper_ai_zxs/whisper_tools.py
whisper_ai_zxs/dd_lib/__init__.py
whisper_ai_zxs/dd_lib/dd_auth_client.py
whisper_ai_zxs/dd_lib/dd_store_client.py
whisper_ai_zxs/jd_lib/__init__.py
whisper_ai_zxs/jd_lib/jd_auth_client.py
whisper_ai_zxs/jd_lib/jd_store_client.py
whisper_ai_zxs/red_lib/__init__.py
whisper_ai_zxs/red_lib/red_auth_client.py
whisper_ai_zxs/red_lib/red_store_client.py
whisper_ai_zxs/wx_lib/__init__.py
whisper_ai_zxs/wx_lib/wx_auth_client.py
whisper_ai_zxs/wx_lib/wx_store_client.py
whisper_ai_zxs-0.2.111.dist-info/licenses/LICENSE
whisper_ai_zxs-0.2.111.dist-info/METADATA
whisper_ai_zxs-0.2.111.dist-info/WHEEL
whisper_ai_zxs-0.2.111.dist-info/top_level.txt
whisper_ai_zxs-0.2.111.dist-info/RECORD
