Metadata-Version: 2.4
Name: whisper_ai_zxs
Version: 0.2.111
Summary: 植想说的AI客服工具
Home-page: https://github.com/yourusername/my_package
Author: 植想说
Author-email: lizhenhua@zxslife.com
Classifier: Programming Language :: Python :: 3
Classifier: License :: OSI Approved :: MIT License
Classifier: Operating System :: OS Independent
License-File: LICENSE
Requires-Dist: openai
Requires-Dist: pymysql
Requires-Dist: requests
Requires-Dist: typing_extensions
Requires-Dist: openpyxl
Requires-Dist: cryptography
Requires-Dist: DBUtils
Requires-Dist: cpca
Dynamic: author
Dynamic: author-email
Dynamic: classifier
Dynamic: description
Dynamic: description-content-type
Dynamic: home-page
Dynamic: license-file
Dynamic: requires-dist
Dynamic: summary
